_foo.cpython-37m-darwin.so
daltons_tensorflow/__init__.py
daltons_tensorflow/python/__init__.py
daltons_tensorflow/python/core/__init__.py
daltons_tensorflow/python/core/_daltons_core.so
daltons_tensorflow/python/core/binding.py
daltons_tensorflow/python/core/metrics.py
daltons_tensorflow/python/core/metrics_test.py
daltons_tensorflow/python/core/policymanagement.py
daltons_tensorflow/python/core/policymanagement_test.py
daltons_tensorflow/python/core/version.py
daltons_tensorflow/python/ops/__init__.py
daltons_tensorflow/python/ops/dataset.py
daltons_tensorflow/python/ops/dataset_test.py
daltons_tensorflow-0.0.25.dist-info/LICENSE.txt
daltons_tensorflow-0.0.25.dist-info/METADATA
daltons_tensorflow-0.0.25.dist-info/WHEEL
daltons_tensorflow-0.0.25.dist-info/top_level.txt
daltons_tensorflow-0.0.25.dist-info/RECORD
